af_cli/__init__.py
af_cli/commands/__init__.py
af_cli/commands/applications.py
af_cli/commands/auth.py
af_cli/commands/config.py
af_cli/commands/tools.py
af_cli/core/__init__.py
af_cli/core/client.py
af_cli/core/config.py
af_cli/core/oauth.py
af_cli/core/output.py
af_cli/core/token_storage.py
af_cli/main.py
af_sdk/__init__.py
af_sdk/auth/__init__.py
af_sdk/auth/applications.py
af_sdk/auth/credentials.py
af_sdk/auth/oauth.py
af_sdk/auth/token_cache.py
af_sdk/connectors/__init__.py
af_sdk/connectors/base.py
af_sdk/connectors/registry.py
af_sdk/exceptions.py
af_sdk/mcp_client.py
af_sdk/models/__init__.py
af_sdk/models/types.py
af_sdk/transport/__init__.py
agentic_fabriq_sdk-0.1.46.dist-info/METADATA
agentic_fabriq_sdk-0.1.46.dist-info/WHEEL
agentic_fabriq_sdk-0.1.46.dist-info/entry_points.txt
agentic_fabriq_sdk-0.1.46.dist-info/RECORD
