Metadata-Version: 2.4
Name: agentic-fabriq-sdk
Version: 0.1.46
Summary: Agentic Fabriq SDK: high-level client, CLI tool, DX helpers, and auth for AI agents
License: Apache-2.0
Keywords: fabriq,agentic-fabriq,sdk,ai,agents,agentic,fabric,cli
Author: Agentic Fabriq Contributors
Author-email: contributors@agentic-fabriq.org
Requires-Python: >=3.11,<3.13
Classifier: Development Status :: 4 - Beta
Classifier: Intended Audience :: Developers
Classifier: License :: OSI Approved :: Apache Software License
Classifier: Programming Language :: Python :: 3
Classifier: Programming Language :: Python :: 3.11
Classifier: Programming Language :: Python :: 3.12
Classifier: Typing :: Typed
Requires-Dist: PyJWT (>=2.8.0)
Requires-Dist: PyYAML (>=6.0.0)
Requires-Dist: aiohttp (>=3.9.0)
Requires-Dist: click (>=8.1.0)
Requires-Dist: cryptography (>=41.0.0)
Requires-Dist: httpx (>=0.25.0)
Requires-Dist: keyring (>=25.0.0)
Requires-Dist: nats-py (>=2.4.0)
Requires-Dist: opentelemetry-api (>=1.20.0)
Requires-Dist: opentelemetry-instrumentation-httpx (>=0.41b0)
Requires-Dist: pydantic (>=2.4.0)
Requires-Dist: rich (>=13.7.0)
Requires-Dist: stevedore (>=5.1.0)
Requires-Dist: typer[all] (>=0.20.0)
Requires-Dist: typing-extensions (>=4.0.0)
Project-URL: Documentation, https://docs.agentic-fabric.org
Project-URL: Homepage, https://github.com/agentic-fabric/agentic-fabric
Project-URL: Repository, https://github.com/agentic-fabric/agentic-fabric
